abdulpy/__init__.py
abdulpy-0.2.dist-info/LICENCE.txt
abdulpy-0.2.dist-info/METADATA
abdulpy-0.2.dist-info/WHEEL
abdulpy-0.2.dist-info/top_level.txt
abdulpy-0.2.dist-info/RECORD
