Metadata-Version: 2.1
Name: abdulpy
Version: 0.2
Summary: A simple library which contains all the programs like simple calculations, loops etc.
Author: Abdul Ahad
Author-email: noperson883@gmail.com
License-File: LICENCE.txt
